<?xml version="1.0" encoding="UTF-8"?><Document xmlns="urn:iso:std:iso:20022:tech:xsd:pacs.002.001.12"><FIToFIPmtStsRpt><GrpHdr><MsgId>PACS002-MSG-BANKA-ISO-INQ4-20260512141827-1778570357067</MsgId><CreDtTm>2026-05-12T07:19:17.066111Z</CreDtTm></GrpHdr><OrgnlGrpInfAndSts><OrgnlMsgId>MSG-BANKA-ISO-INQ4-20260512141827</OrgnlMsgId><OrgnlMsgNmId>pacs.008.001.12</OrgnlMsgNmId><GrpSts>RJCT</GrpSts></OrgnlGrpInfAndSts><TxInfAndSts><OrgnlInstrId>INST-BANKA-ISO-INQ4-20260512141827</OrgnlInstrId><OrgnlEndToEndId>E2E-BANKA-ISO-INQ4-20260512141827</OrgnlEndToEndId><TxSts>RJCT</TxSts><StsRsnInf><Rsn><Cd>MS03</Cd></Rsn><AddtlInf>Unable to persist inbound PACS.008: InquiryRef is not eligible for transfer: INQ-20260512T13582-6546D1BF, status=USED</AddtlInf></StsRsnInf></TxInfAndSts></FIToFIPmtStsRpt></Document>